jack_audio_player/__init__.py
jack_audio_player-1.0.2.dist-info/LICENSE
jack_audio_player-1.0.2.dist-info/WHEEL
jack_audio_player-1.0.2.dist-info/METADATA
jack_audio_player-1.0.2.dist-info/RECORD
