Metadata-Version: 2.1
Name: jack_audio_player
Version: 1.0.2
Summary: Python Jack client which plays audio files.
Author-email: Leon Dionne <ldionne@dridesign.sh.cn>
Classifier: License :: OSI Approved :: GNU General Public License v3 or later (GPLv3+)
Classifier: Programming Language :: Python
Classifier: Programming Language :: Python :: 3.10
Classifier: Topic :: Multimedia :: Sound/Audio :: Sound Synthesis
Classifier: Topic :: Multimedia :: Sound/Audio :: MIDI
Requires-Dist: JACK-Client
Requires-Dist: numpy
Requires-Dist: soundfile
Project-URL: Home, https://github.com/Zen-Master-SoSo/jack_audio_player
